wikisource/__init__.py
wikisource/chapter.py
wikisource/cli.py
wikisource/collection.py
wikisource/paragraph.py
wikisource/source.py
wikisource/webpage.py
wikisource-0.0.12.dist-info/LICENSE
wikisource-0.0.12.dist-info/METADATA
wikisource-0.0.12.dist-info/WHEEL
wikisource-0.0.12.dist-info/entry_points.txt
wikisource-0.0.12.dist-info/top_level.txt
wikisource-0.0.12.dist-info/RECORD
