Metadata-Version: 2.1
Name: wikisource
Version: 0.0.12
Summary: A python package to search in books available on wikisource.org
Author-email: "Mathieu G." <mathieu6700417@gmail.com>
Project-URL: Homepage, https://github.com/mathieu6700417/wikisource
Project-URL: Bug Tracker, https://github.com/mathieu6700417/wikisource/issues
License-File: LICENSE
Requires-Dist: requests
Requires-Dist: bs4
